{
  "project_info": {
    "project_number": "437064787935",
    "project_id": "chap-app-masterclass",
    "storage_bucket": "chap-app-masterclass.appspot.com"
  },
  "client": [
    {
      "client_info": {
        "mobilesdk_app_id": "1:437064787935:android:3f9dd55201a8dd9301c66a",
        "android_client_info": {
          "package_name": "com.example.chapAppMasterclass"
        }
      },
      "oauth_client": [],
      "api_key": [
        {
          "current_key": "AIzaSyArmX0QqgHSc4uPiD_ndL7Uc_rQ8MZxYGU"
        }
      ],
      "services": {
        "appinvite_service": {
          "other_platform_oauth_client": []
        }
      }
    }
  ],
  "configuration_version": "1"
}